{
	"configurations" : 
	[
		{
			"directories" : 
			[
				{
					"build" : ".",
					"childIndexes" : 
					[
						1
					],
					"hasInstallRule" : true,
					"jsonFile" : "directory-.-Debug-d0094a50bb2071803777.json",
					"minimumCMakeVersion" : 
					{
						"string" : "3.14"
					},
					"projectIndex" : 0,
					"source" : ".",
					"targetIndexes" : 
					[
						0,
						2,
						4
					]
				},
				{
					"build" : "glfw",
					"childIndexes" : 
					[
						2,
						3
					],
					"hasInstallRule" : true,
					"jsonFile" : "directory-glfw-Debug-c744de03ddd31a61447f.json",
					"minimumCMakeVersion" : 
					{
						"string" : "3.4"
					},
					"parentIndex" : 0,
					"projectIndex" : 1,
					"source" : "glfw",
					"targetIndexes" : 
					[
						1,
						5
					]
				},
				{
					"build" : "glfw/src",
					"hasInstallRule" : true,
					"jsonFile" : "directory-glfw.src-Debug-400dc938992e2775e3b8.json",
					"minimumCMakeVersion" : 
					{
						"string" : "3.4"
					},
					"parentIndex" : 1,
					"projectIndex" : 1,
					"source" : "glfw/src",
					"targetIndexes" : 
					[
						3,
						6
					]
				},
				{
					"build" : "glfw/docs",
					"jsonFile" : "directory-glfw.docs-Debug-21df72f16f419b0b0042.json",
					"minimumCMakeVersion" : 
					{
						"string" : "3.4"
					},
					"parentIndex" : 1,
					"projectIndex" : 1,
					"source" : "glfw/docs"
				}
			],
			"name" : "Debug",
			"projects" : 
			[
				{
					"childIndexes" : 
					[
						1
					],
					"directoryIndexes" : 
					[
						0
					],
					"name" : "paulinator",
					"targetIndexes" : 
					[
						0,
						2,
						4
					]
				},
				{
					"directoryIndexes" : 
					[
						1,
						2,
						3
					],
					"name" : "GLFW",
					"parentIndex" : 0,
					"targetIndexes" : 
					[
						1,
						3,
						5,
						6
					]
				}
			],
			"targets" : 
			[
				{
					"directoryIndex" : 0,
					"id" : "ALL_BUILD::@6890427a1f51a3e7e1df",
					"jsonFile" : "target-ALL_BUILD-Debug-8c21445eaa6ce5a9b675.json",
					"name" : "ALL_BUILD",
					"projectIndex" : 0
				},
				{
					"directoryIndex" : 1,
					"id" : "ALL_BUILD::@eb154563b92743f6cbb3",
					"jsonFile" : "target-ALL_BUILD-Debug-474c2ac6a44f38cbee6c.json",
					"name" : "ALL_BUILD",
					"projectIndex" : 1
				},
				{
					"directoryIndex" : 0,
					"id" : "ZERO_CHECK::@6890427a1f51a3e7e1df",
					"jsonFile" : "target-ZERO_CHECK-Debug-07a01c9df0542e137dc0.json",
					"name" : "ZERO_CHECK",
					"projectIndex" : 0
				},
				{
					"directoryIndex" : 2,
					"id" : "glfw::@12507ebf64a5258d241e",
					"jsonFile" : "target-glfw-Debug-6ea65c2f11f947939ea0.json",
					"name" : "glfw",
					"projectIndex" : 1
				},
				{
					"directoryIndex" : 0,
					"id" : "paulinator::@6890427a1f51a3e7e1df",
					"jsonFile" : "target-paulinator-Debug-4194e3288b2fab525458.json",
					"name" : "paulinator",
					"projectIndex" : 0
				},
				{
					"directoryIndex" : 1,
					"id" : "uninstall::@eb154563b92743f6cbb3",
					"jsonFile" : "target-uninstall-Debug-507bc1d5d396f9bea5a4.json",
					"name" : "uninstall",
					"projectIndex" : 1
				},
				{
					"directoryIndex" : 2,
					"id" : "update_mappings::@12507ebf64a5258d241e",
					"jsonFile" : "target-update_mappings-Debug-258a750125f0b1c25551.json",
					"name" : "update_mappings",
					"projectIndex" : 1
				}
			]
		},
		{
			"directories" : 
			[
				{
					"build" : ".",
					"childIndexes" : 
					[
						1
					],
					"hasInstallRule" : true,
					"jsonFile" : "directory-.-Release-d0094a50bb2071803777.json",
					"minimumCMakeVersion" : 
					{
						"string" : "3.14"
					},
					"projectIndex" : 0,
					"source" : ".",
					"targetIndexes" : 
					[
						0,
						2,
						4
					]
				},
				{
					"build" : "glfw",
					"childIndexes" : 
					[
						2,
						3
					],
					"hasInstallRule" : true,
					"jsonFile" : "directory-glfw-Release-c744de03ddd31a61447f.json",
					"minimumCMakeVersion" : 
					{
						"string" : "3.4"
					},
					"parentIndex" : 0,
					"projectIndex" : 1,
					"source" : "glfw",
					"targetIndexes" : 
					[
						1,
						5
					]
				},
				{
					"build" : "glfw/src",
					"hasInstallRule" : true,
					"jsonFile" : "directory-glfw.src-Release-6d7f24f335e6186c13ab.json",
					"minimumCMakeVersion" : 
					{
						"string" : "3.4"
					},
					"parentIndex" : 1,
					"projectIndex" : 1,
					"source" : "glfw/src",
					"targetIndexes" : 
					[
						3,
						6
					]
				},
				{
					"build" : "glfw/docs",
					"jsonFile" : "directory-glfw.docs-Release-21df72f16f419b0b0042.json",
					"minimumCMakeVersion" : 
					{
						"string" : "3.4"
					},
					"parentIndex" : 1,
					"projectIndex" : 1,
					"source" : "glfw/docs"
				}
			],
			"name" : "Release",
			"projects" : 
			[
				{
					"childIndexes" : 
					[
						1
					],
					"directoryIndexes" : 
					[
						0
					],
					"name" : "paulinator",
					"targetIndexes" : 
					[
						0,
						2,
						4
					]
				},
				{
					"directoryIndexes" : 
					[
						1,
						2,
						3
					],
					"name" : "GLFW",
					"parentIndex" : 0,
					"targetIndexes" : 
					[
						1,
						3,
						5,
						6
					]
				}
			],
			"targets" : 
			[
				{
					"directoryIndex" : 0,
					"id" : "ALL_BUILD::@6890427a1f51a3e7e1df",
					"jsonFile" : "target-ALL_BUILD-Release-8c21445eaa6ce5a9b675.json",
					"name" : "ALL_BUILD",
					"projectIndex" : 0
				},
				{
					"directoryIndex" : 1,
					"id" : "ALL_BUILD::@eb154563b92743f6cbb3",
					"jsonFile" : "target-ALL_BUILD-Release-474c2ac6a44f38cbee6c.json",
					"name" : "ALL_BUILD",
					"projectIndex" : 1
				},
				{
					"directoryIndex" : 0,
					"id" : "ZERO_CHECK::@6890427a1f51a3e7e1df",
					"jsonFile" : "target-ZERO_CHECK-Release-07a01c9df0542e137dc0.json",
					"name" : "ZERO_CHECK",
					"projectIndex" : 0
				},
				{
					"directoryIndex" : 2,
					"id" : "glfw::@12507ebf64a5258d241e",
					"jsonFile" : "target-glfw-Release-11e6c2cc136f0ca4d466.json",
					"name" : "glfw",
					"projectIndex" : 1
				},
				{
					"directoryIndex" : 0,
					"id" : "paulinator::@6890427a1f51a3e7e1df",
					"jsonFile" : "target-paulinator-Release-2bd026df51b588932609.json",
					"name" : "paulinator",
					"projectIndex" : 0
				},
				{
					"directoryIndex" : 1,
					"id" : "uninstall::@eb154563b92743f6cbb3",
					"jsonFile" : "target-uninstall-Release-507bc1d5d396f9bea5a4.json",
					"name" : "uninstall",
					"projectIndex" : 1
				},
				{
					"directoryIndex" : 2,
					"id" : "update_mappings::@12507ebf64a5258d241e",
					"jsonFile" : "target-update_mappings-Release-258a750125f0b1c25551.json",
					"name" : "update_mappings",
					"projectIndex" : 1
				}
			]
		},
		{
			"directories" : 
			[
				{
					"build" : ".",
					"childIndexes" : 
					[
						1
					],
					"hasInstallRule" : true,
					"jsonFile" : "directory-.-MinSizeRel-d0094a50bb2071803777.json",
					"minimumCMakeVersion" : 
					{
						"string" : "3.14"
					},
					"projectIndex" : 0,
					"source" : ".",
					"targetIndexes" : 
					[
						0,
						2,
						4
					]
				},
				{
					"build" : "glfw",
					"childIndexes" : 
					[
						2,
						3
					],
					"hasInstallRule" : true,
					"jsonFile" : "directory-glfw-MinSizeRel-c744de03ddd31a61447f.json",
					"minimumCMakeVersion" : 
					{
						"string" : "3.4"
					},
					"parentIndex" : 0,
					"projectIndex" : 1,
					"source" : "glfw",
					"targetIndexes" : 
					[
						1,
						5
					]
				},
				{
					"build" : "glfw/src",
					"hasInstallRule" : true,
					"jsonFile" : "directory-glfw.src-MinSizeRel-096465e206d66a627fc5.json",
					"minimumCMakeVersion" : 
					{
						"string" : "3.4"
					},
					"parentIndex" : 1,
					"projectIndex" : 1,
					"source" : "glfw/src",
					"targetIndexes" : 
					[
						3,
						6
					]
				},
				{
					"build" : "glfw/docs",
					"jsonFile" : "directory-glfw.docs-MinSizeRel-21df72f16f419b0b0042.json",
					"minimumCMakeVersion" : 
					{
						"string" : "3.4"
					},
					"parentIndex" : 1,
					"projectIndex" : 1,
					"source" : "glfw/docs"
				}
			],
			"name" : "MinSizeRel",
			"projects" : 
			[
				{
					"childIndexes" : 
					[
						1
					],
					"directoryIndexes" : 
					[
						0
					],
					"name" : "paulinator",
					"targetIndexes" : 
					[
						0,
						2,
						4
					]
				},
				{
					"directoryIndexes" : 
					[
						1,
						2,
						3
					],
					"name" : "GLFW",
					"parentIndex" : 0,
					"targetIndexes" : 
					[
						1,
						3,
						5,
						6
					]
				}
			],
			"targets" : 
			[
				{
					"directoryIndex" : 0,
					"id" : "ALL_BUILD::@6890427a1f51a3e7e1df",
					"jsonFile" : "target-ALL_BUILD-MinSizeRel-8c21445eaa6ce5a9b675.json",
					"name" : "ALL_BUILD",
					"projectIndex" : 0
				},
				{
					"directoryIndex" : 1,
					"id" : "ALL_BUILD::@eb154563b92743f6cbb3",
					"jsonFile" : "target-ALL_BUILD-MinSizeRel-474c2ac6a44f38cbee6c.json",
					"name" : "ALL_BUILD",
					"projectIndex" : 1
				},
				{
					"directoryIndex" : 0,
					"id" : "ZERO_CHECK::@6890427a1f51a3e7e1df",
					"jsonFile" : "target-ZERO_CHECK-MinSizeRel-07a01c9df0542e137dc0.json",
					"name" : "ZERO_CHECK",
					"projectIndex" : 0
				},
				{
					"directoryIndex" : 2,
					"id" : "glfw::@12507ebf64a5258d241e",
					"jsonFile" : "target-glfw-MinSizeRel-7added37b96c95072cf9.json",
					"name" : "glfw",
					"projectIndex" : 1
				},
				{
					"directoryIndex" : 0,
					"id" : "paulinator::@6890427a1f51a3e7e1df",
					"jsonFile" : "target-paulinator-MinSizeRel-7846ebbdfb348c163421.json",
					"name" : "paulinator",
					"projectIndex" : 0
				},
				{
					"directoryIndex" : 1,
					"id" : "uninstall::@eb154563b92743f6cbb3",
					"jsonFile" : "target-uninstall-MinSizeRel-507bc1d5d396f9bea5a4.json",
					"name" : "uninstall",
					"projectIndex" : 1
				},
				{
					"directoryIndex" : 2,
					"id" : "update_mappings::@12507ebf64a5258d241e",
					"jsonFile" : "target-update_mappings-MinSizeRel-258a750125f0b1c25551.json",
					"name" : "update_mappings",
					"projectIndex" : 1
				}
			]
		},
		{
			"directories" : 
			[
				{
					"build" : ".",
					"childIndexes" : 
					[
						1
					],
					"hasInstallRule" : true,
					"jsonFile" : "directory-.-RelWithDebInfo-d0094a50bb2071803777.json",
					"minimumCMakeVersion" : 
					{
						"string" : "3.14"
					},
					"projectIndex" : 0,
					"source" : ".",
					"targetIndexes" : 
					[
						0,
						2,
						4
					]
				},
				{
					"build" : "glfw",
					"childIndexes" : 
					[
						2,
						3
					],
					"hasInstallRule" : true,
					"jsonFile" : "directory-glfw-RelWithDebInfo-c744de03ddd31a61447f.json",
					"minimumCMakeVersion" : 
					{
						"string" : "3.4"
					},
					"parentIndex" : 0,
					"projectIndex" : 1,
					"source" : "glfw",
					"targetIndexes" : 
					[
						1,
						5
					]
				},
				{
					"build" : "glfw/src",
					"hasInstallRule" : true,
					"jsonFile" : "directory-glfw.src-RelWithDebInfo-a2936a8682f84afb4edc.json",
					"minimumCMakeVersion" : 
					{
						"string" : "3.4"
					},
					"parentIndex" : 1,
					"projectIndex" : 1,
					"source" : "glfw/src",
					"targetIndexes" : 
					[
						3,
						6
					]
				},
				{
					"build" : "glfw/docs",
					"jsonFile" : "directory-glfw.docs-RelWithDebInfo-21df72f16f419b0b0042.json",
					"minimumCMakeVersion" : 
					{
						"string" : "3.4"
					},
					"parentIndex" : 1,
					"projectIndex" : 1,
					"source" : "glfw/docs"
				}
			],
			"name" : "RelWithDebInfo",
			"projects" : 
			[
				{
					"childIndexes" : 
					[
						1
					],
					"directoryIndexes" : 
					[
						0
					],
					"name" : "paulinator",
					"targetIndexes" : 
					[
						0,
						2,
						4
					]
				},
				{
					"directoryIndexes" : 
					[
						1,
						2,
						3
					],
					"name" : "GLFW",
					"parentIndex" : 0,
					"targetIndexes" : 
					[
						1,
						3,
						5,
						6
					]
				}
			],
			"targets" : 
			[
				{
					"directoryIndex" : 0,
					"id" : "ALL_BUILD::@6890427a1f51a3e7e1df",
					"jsonFile" : "target-ALL_BUILD-RelWithDebInfo-8c21445eaa6ce5a9b675.json",
					"name" : "ALL_BUILD",
					"projectIndex" : 0
				},
				{
					"directoryIndex" : 1,
					"id" : "ALL_BUILD::@eb154563b92743f6cbb3",
					"jsonFile" : "target-ALL_BUILD-RelWithDebInfo-474c2ac6a44f38cbee6c.json",
					"name" : "ALL_BUILD",
					"projectIndex" : 1
				},
				{
					"directoryIndex" : 0,
					"id" : "ZERO_CHECK::@6890427a1f51a3e7e1df",
					"jsonFile" : "target-ZERO_CHECK-RelWithDebInfo-07a01c9df0542e137dc0.json",
					"name" : "ZERO_CHECK",
					"projectIndex" : 0
				},
				{
					"directoryIndex" : 2,
					"id" : "glfw::@12507ebf64a5258d241e",
					"jsonFile" : "target-glfw-RelWithDebInfo-6ca22020e2b32c3e4aaf.json",
					"name" : "glfw",
					"projectIndex" : 1
				},
				{
					"directoryIndex" : 0,
					"id" : "paulinator::@6890427a1f51a3e7e1df",
					"jsonFile" : "target-paulinator-RelWithDebInfo-131a52202ee3b7fe8172.json",
					"name" : "paulinator",
					"projectIndex" : 0
				},
				{
					"directoryIndex" : 1,
					"id" : "uninstall::@eb154563b92743f6cbb3",
					"jsonFile" : "target-uninstall-RelWithDebInfo-507bc1d5d396f9bea5a4.json",
					"name" : "uninstall",
					"projectIndex" : 1
				},
				{
					"directoryIndex" : 2,
					"id" : "update_mappings::@12507ebf64a5258d241e",
					"jsonFile" : "target-update_mappings-RelWithDebInfo-258a750125f0b1c25551.json",
					"name" : "update_mappings",
					"projectIndex" : 1
				}
			]
		}
	],
	"kind" : "codemodel",
	"paths" : 
	{
		"build" : "C:/Users/JOEL/OneDrive/Documents/xi9d/projects/xi9d engine/build",
		"source" : "C:/Users/JOEL/OneDrive/Documents/xi9d/projects/xi9d engine"
	},
	"version" : 
	{
		"major" : 2,
		"minor" : 7
	}
}
